fairseq/registry.py
fairseq/trainer.py
fairseq/speech_generator.py
fairseq/search.py
fairseq/nan_detector.py
fairseq/quantization_utils.py
fairseq/libbleu.cpython-37m-x86_64-linux-gnu.so
fairseq/tokenizer.py
fairseq/iterative_refinement_generator.py
fairseq/utils.py
fairseq/hub_utils.py
fairseq/file_utils.py
fairseq/checkpoint_utils.py
fairseq/token_generation_constraints.py
fairseq/pdb.py
fairseq/ngram_repeat_block.py
fairseq/sequence_scorer.py
fairseq/sequence_generator.py
fairseq/file_chunker_utils.py
fairseq/file_io.py
fairseq/options.py
fairseq/binarizer.py
fairseq/incremental_decoding_utils.py
fairseq/version.py
fairseq/__init__.py
fairseq/data/numel_dataset.py
fairseq/data/resampling_dataset.py
fairseq/data/id_dataset.py
fairseq/data/transform_eos_lang_pair_dataset.py
fairseq/data/shorten_dataset.py
fairseq/data/language_pair_dataset.py
fairseq/data/prepend_dataset.py
fairseq/data/list_dataset.py
fairseq/data/replace_dataset.py
fairseq/data/iterators.py
fairseq/data/fairseq_dataset.py
fairseq/data/nested_dictionary_dataset.py
fairseq/data/text_compressor.py
fairseq/data/backtranslation_dataset.py
fairseq/data/token_block_dataset.py
fairseq/data/token_block_utils_fast.cpython-37m-x86_64-linux-gnu.so
fairseq/data/denoising_dataset.py
fairseq/data/strip_token_dataset.py
fairseq/data/sort_dataset.py
fairseq/data/lm_context_window_dataset.py
fairseq/data/multi_corpus_dataset.py
fairseq/data/round_robin_zip_datasets.py
fairseq/data/fasta_dataset.py
fairseq/data/roll_dataset.py
fairseq/data/raw_label_dataset.py
fairseq/data/prepend_token_dataset.py
fairseq/data/lru_cache_dataset.py
fairseq/data/transform_eos_dataset.py
fairseq/data/bucket_pad_length_dataset.py
fairseq/data/add_target_dataset.py
fairseq/data/concat_dataset.py
fairseq/data/monolingual_dataset.py
fairseq/data/pad_dataset.py
fairseq/data/concat_sentences_dataset.py
fairseq/data/codedataset.py
fairseq/data/base_wrapper_dataset.py
fairseq-0.12.2.dist-info/top_level.txt
fairseq-0.12.2.dist-info/entry_points.txt
fairseq-0.12.2.dist-info/WHEEL
fairseq-0.12.2.dist-info/LICENSE
fairseq-0.12.2.dist-info/METADATA
fairseq-0.12.2.dist-info/RECORD
