Metadata-Version: 2.1
Name: fairseq
Version: 0.12.2
Summary: Facebook AI Research Sequence-to-Sequence Toolkit
Home-page: https://github.com/pytorch/fairseq
License: UNKNOWN
Platform: UNKNOWN
Classifier: Intended Audience :: Science/Research
Classifier: License :: OSI Approved :: MIT License
Classifier: Programming Language :: Python :: 3.6
Classifier: Programming Language :: Python :: 3.7
Classifier: Programming Language :: Python :: 3.8
Classifier: Topic :: Scientific/Engineering :: Artificial Intelligence
License-File: LICENSE
Requires-Dist: cffi
Requires-Dist: cython
Requires-Dist: hydra-core (<1.1,>=1.0.7)
Requires-Dist: omegaconf (<2.1)
Requires-Dist: regex
Requires-Dist: sacrebleu (>=1.4.12)
Requires-Dist: torch
Requires-Dist: tqdm
Requires-Dist: bitarray
Requires-Dist: torchaudio (>=0.8.0)
Requires-Dist: dataclasses ; python_version < "3.7"
Requires-Dist: numpy (<1.20.0) ; python_version < "3.7"
Requires-Dist: numpy ; python_version >= "3.7"
